datasetutils/__init__.py
datasetutils/datasets.py
datasetutils/mutations.py
datasetutils/pasting.py
datasetutils-0.1.1.dist-info/LICENSE
datasetutils-0.1.1.dist-info/METADATA
datasetutils-0.1.1.dist-info/WHEEL
datasetutils-0.1.1.dist-info/top_level.txt
datasetutils-0.1.1.dist-info/RECORD
