Metadata-Version: 2.1
Name: datasetutils
Version: 0.1.1
Summary: A simple util to make your dataset flexable.
Home-page: https://github.com/Trapov/dataset-utils
Author: Dmitry Afonin
Author-email: raysofgoodness@gmail.com
License: MIT
Platform: UNKNOWN
Classifier: Programming Language :: Python :: 3
Classifier: License :: OSI Approved :: MIT License
Classifier: Operating System :: OS Independent
Requires-Dist: pillow (==6.1.0)
